nextpipe/__about__.py
nextpipe/__init__.py
nextpipe/config.py
nextpipe/decorators.py
nextpipe/flow.py
nextpipe/graph.py
nextpipe/schema.py
nextpipe/threads.py
nextpipe/uplink.py
nextpipe/utils.py
nextpipe-0.6.0.dist-info/METADATA
nextpipe-0.6.0.dist-info/WHEEL
nextpipe-0.6.0.dist-info/licenses/LICENSE.md
nextpipe-0.6.0.dist-info/RECORD
