Metadata-Version: 2.4
Name: nextpipe
Version: 0.6.0
Summary: Framework for Decision Pipeline modeling and execution
Project-URL: Homepage, https://www.nextmv.io
Project-URL: Documentation, https://nextpipe.docs.nextmv.io/en/latest/
Project-URL: Repository, https://github.com/nextmv-io/nextpipe
Author-email: Nextmv <tech@nextmv.io>
Maintainer-email: Nextmv <tech@nextmv.io>
License: # LICENSE
License-File: LICENSE.md
Keywords: decision automation,decision engineering,decision pipelines,decision science,decision workflows,decisions,nextmv,operations research,optimization,pipelines,workflows
Classifier: Operating System :: OS Independent
Classifier: Programming Language :: Python :: 3
Classifier: Programming Language :: Python :: 3.10
Classifier: Programming Language :: Python :: 3.11
Classifier: Programming Language :: Python :: 3.12
Classifier: Programming Language :: Python :: 3.13
Classifier: Programming Language :: Python :: 3.14
Requires-Python: >=3.10
Requires-Dist: dataclasses-json>=0.6.7
Requires-Dist: nextmv>=0.40.0
Requires-Dist: requests>=2.31.0
Provides-Extra: dev
Requires-Dist: goldie>=0.1.8; extra == 'dev'
Requires-Dist: ruff>=0.11.6; extra == 'dev'
